prombzex/__init__.py
prombzex/config.py
prombzex/prombzex.py
prombzex/promify.py
prombzex/server.py
prombzex-0.3.data/scripts/prombzex
tests/__init__.py
tests/test_config.py
prombzex-0.3.dist-info/LICENSE
prombzex-0.3.dist-info/METADATA
prombzex-0.3.dist-info/WHEEL
prombzex-0.3.dist-info/top_level.txt
prombzex-0.3.dist-info/RECORD
