Metadata-Version: 2.1
Name: prombzex
Version: 0.3
Summary: Prometheus Bugzilla Exporter
Home-page: https://github.com/cmsj/prombzex
Author: Chris Jones
Author-email: cmsj@tenshu.net
License: UNKNOWN
Platform: UNKNOWN
Classifier: Programming Language :: Python :: 3
Classifier: License :: OSI Approved :: MIT License
Classifier: Operating System :: OS Independent
